code_annotator/__init__.py
code_annotator/annotator.py
code_annotator-2025.5.100925.dist-info/licenses/LICENSE
code_annotator-2025.5.100925.dist-info/METADATA
code_annotator-2025.5.100925.dist-info/WHEEL
code_annotator-2025.5.100925.dist-info/entry_points.txt
code_annotator-2025.5.100925.dist-info/top_level.txt
code_annotator-2025.5.100925.dist-info/RECORD
